gpdt/__init__.py
gpdt/definitions.py
gpdt/gpdt.py
gpdt/cli/__init__.py
gpdt/cli/config.py
gpdt/cli/inventory.py
gpdt/cli/main.py
gpdt/cli/publish.py
gpdt/cli/script.py
gpdt/cli/setup.py
gpdt/cli/task.py
gpdt/cli/wingdbstub.py
gpdt/cli/workspace.py
gpdt/helpers/__init__.py
gpdt/helpers/faker.py
gpdt/helpers/general.py
gpdt/helpers/loaders.py
gpdt/helpers/models.py
gpdt/helpers/surreal.py
gpdt/logic/__init__.py
gpdt/logic/beacons.py
gpdt/logic/inventory.py
gpdt/mappers/__init__.py
gpdt/mappers/beacons.py
gpdt/models/__init__.py
gpdt/models/base.py
gpdt/models/beacons.py
gpdt/models/config.py
gpdt/models/enums.py
gpdt/models/gpdt.py
gpdt/models/inventory.py
gpdt/models/script.py
gpdt/models/task.py
gpdt/ports/__init__.py
gpdt/ports/beacons.py
gpdt/ports/preferences.py
gpdt/storage/__init__.py
gpdt/storage/surreal.py
gpdt-0.1.0.dist-info/AUTHORS.rst
gpdt-0.1.0.dist-info/LICENSE
gpdt-0.1.0.dist-info/METADATA
gpdt-0.1.0.dist-info/WHEEL
gpdt-0.1.0.dist-info/entry_points.txt
gpdt-0.1.0.dist-info/top_level.txt
gpdt-0.1.0.dist-info/RECORD
